[
{"tipo": "unico", "arbitro": "Daniele Orsato", "links": 1, "score": ["0", "1"], "estadio": "Estádio da Luz", "fecha": "Sun, 8/23/20", "hora": "9:00 PM", "fase": "grupos", "nombre_local": "Paris Saint-Germain", "nombre_goleadores_locales_asistentes": [], "tarjetas_locales": ["Leandro Paredes", "Neymar", "Thiago Silva", "Layvin Kurzawa"], "tipo_de_tarjeta_local": [" Yellow card", " Yellow card", " Yellow card", " Yellow card"], "nombre_visitante": "Bayern Munich", "nombre_goleadores_visitantes_asistentes": ["Kingsley Coman", "Joshua Kimmich"], "tarjetas_visitantes": ["Alphonso Davies", "Serge Gnabry", "Niklas Süle", "Thomas Müller"], "tipo_de_tarjeta_visitantes": [" Yellow card", " Yellow card", " Yellow card", " Yellow card"]}
]